CHANGES.txt
DEPENDENCES.txt
README.txt
setup.py
src/ng/__init__.py
src/ng.skin.freeyellow.egg-info/PKG-INFO
src/ng.skin.freeyellow.egg-info/SOURCES.txt
src/ng.skin.freeyellow.egg-info/dependency_links.txt
src/ng.skin.freeyellow.egg-info/namespace_packages.txt
src/ng.skin.freeyellow.egg-info/not-zip-safe
src/ng.skin.freeyellow.egg-info/requires.txt
src/ng.skin.freeyellow.egg-info/top_level.txt
src/ng/skin/freeyellow/__init__.py
src/ng/skin/freeyellow/configure.zcml
src/ng/skin/freeyellow/interfaces.py
src/ng/skin/freeyellow/ng.skin.freeyellow.txt
src/ng/skin/freeyellow/orderinformation.py
src/ng/skin/freeyellow/skeleton.pt
src/ng/skin/freeyellow/style.css
src/ng/skin/freeyellow/style_ie.css
src/ng/skin/freeyellow/etc/ng.skin.freeyellow-configure.zcml
src/ng/skin/freeyellow/viewlet/__init__.py
src/ng/skin/freeyellow/viewlet/configure.zcml
src/ng/skin/freeyellow/viewlet/viewletprojectbox/__init__.py
src/ng/skin/freeyellow/viewlet/viewletprojectbox/configure.zcml
src/ng/skin/freeyellow/viewlet/viewletprojectbox/interfaces.py
src/ng/skin/freeyellow/viewlet/viewletprojectbox/projectbox.pt
src/ng/skin/freeyellow/viewlet/viewletprojectbox/projectbox.py
src/ng/skin/freeyellow/viewlet/viewletsearchbox/__init__.py
src/ng/skin/freeyellow/viewlet/viewletsearchbox/configure.zcml
src/ng/skin/freeyellow/viewlet/viewletsearchbox/interfaces.py
src/ng/skin/freeyellow/viewlet/viewletsearchbox/searchbox.pt
src/ng/skin/freeyellow/viewletleftcolumn/__init__.py
src/ng/skin/freeyellow/viewletleftcolumn/configure.zcml
src/ng/skin/freeyellow/viewletleftcolumn/interfaces.py
src/ng/skin/freeyellow/viewletleftcolumn/viewletleftcolumn.pt